Metadata-Version: 2.1
Name: EntryMaven
Version: 0.0.3
Summary: Simple and efficient customizable logger for Python
Author: Leonardo Cardillo
License: MIT License
Keywords: entrymaven entry maven leoncardi leonardo cardillo custom customizable logger loggers logging logs log
License-File: LICENSE
